herenow_demo/__init__.py
herenow_demo/configure_demo.py
herenow_demo/main.py
herenow_demo/setup_drop_build.py
herenow_demo/static/audio/pitter-patter-thunder.mp3
herenow_demo/static/audio/rain.mp3
herenow_demo/static/css/font-awesome.min.css
herenow_demo/static/css/styles.css
herenow_demo/static/fonts/FontAwesome.otf
herenow_demo/static/fonts/fontawesome-webfont.eot
herenow_demo/static/fonts/fontawesome-webfont.svg
herenow_demo/static/fonts/fontawesome-webfont.ttf
herenow_demo/static/fonts/fontawesome-webfont.woff
herenow_demo/static/fonts/fontawesome-webfont.woff2
herenow_demo/static/js/scripts.js
herenow_demo/templates/here_base.html
herenow_demo/templates/here_partial.html
herenow_demo/templates/index.html
herenow_demo/templates/where.html
herenow_demo/utils/__init__.py
herenow_demo/utils/constants.py
herenow_demo-1.1.2.dist-info/METADATA
herenow_demo-1.1.2.dist-info/WHEEL
herenow_demo-1.1.2.dist-info/entry_points.txt
herenow_demo-1.1.2.dist-info/RECORD
