Metadata-Version: 2.1
Name: herenow-demo
Version: 1.1.2
Summary: Demo of Approximate Retrieval capability of LLMs appplied to build a product for Mindful Exploration of Urban Events.
License: CC BY NC
Author: Sid
Author-email: itissid@gmail.com
Requires-Python: >=3.10,<4.0
Classifier: License :: Other/Proprietary License
Classifier: Programming Language :: Python :: 3
Classifier: Programming Language :: Python :: 3.10
Classifier: Programming Language :: Python :: 3.11
Provides-Extra: quality
Requires-Dist: Jinja2 (>=3.1.2,<4.0.0)
Requires-Dist: SQLAlchemy (==2.0.18)
Requires-Dist: drop-backend (==1.1.3a0)
Requires-Dist: fastapi (>=0.103.0,<0.104.0)
Requires-Dist: gunicorn (>=21.2.0,<22.0.0)
Requires-Dist: itsdangerous (>=2.1.2,<3.0.0)
Requires-Dist: mypy[dmypy] (>=1.7.0,<2.0.0) ; extra == "quality"
Requires-Dist: python-dotenv (>=1.0.0,<2.0.0)
Requires-Dist: pytz (==2023.3)
Requires-Dist: semver (>=3.0.2,<4.0.0)
Requires-Dist: shapely (>=2.0.2,<3.0.0)
Requires-Dist: tomlkit (>=0.12.2,<0.13.0)
Requires-Dist: uvicorn (>=0.23.2,<0.24.0)
